llama_index/indices/managed/dashscope/__init__.py
llama_index/indices/managed/dashscope/api_utils.py
llama_index/indices/managed/dashscope/base.py
llama_index/indices/managed/dashscope/constants.py
llama_index/indices/managed/dashscope/retriever.py
llama_index/indices/managed/dashscope/transformations.py
llama_index/indices/managed/dashscope/utils.py
llama_index_indices_managed_dashscope-0.4.1.dist-info/METADATA
llama_index_indices_managed_dashscope-0.4.1.dist-info/WHEEL
llama_index_indices_managed_dashscope-0.4.1.dist-info/licenses/LICENSE
llama_index_indices_managed_dashscope-0.4.1.dist-info/RECORD
