Metadata-Version: 2.4
Name: llama-index-indices-managed-dashscope
Version: 0.4.1
Summary: llama-index indices managed-dashscope integration
Author-email: Ruixue Ding <ada.drx@alibaba-inc.com>
License-Expression: MIT
License-File: LICENSE
Requires-Python: <4.0,>=3.9
Requires-Dist: llama-index-core<0.15,>=0.13.0
Requires-Dist: llama-index-embeddings-dashscope<0.5,>=0.4.0
Requires-Dist: llama-index-node-parser-dashscope<0.6,>=0.5.0
Requires-Dist: llama-index-readers-dashscope<0.5,>=0.4.0
